Metadata-Version: 1.1
Name: tkPopup
Version: 0.0.9
Summary: extension to Tkinter: 3 popup classes for user interaction
Home-page: http://packages.python.org/tkPopup
Author: Franz Beck
Author-email: fbeck@intekom.co.za
License: BSD
Keywords: tkinter popup user-interaction
Platform: UNKNOWN
Classifier: Development Status :: 3 - Alpha
Classifier: Intended Audience :: Developers
Classifier: Programming Language :: Python :: 2
Classifier: Programming Language :: Python :: 2.7
Classifier: Programming Language :: Python :: 3
Classifier: Topic :: Utilities
Classifier: Topic :: Software Development :: Libraries :: Python Modules
Classifier: License :: OSI Approved :: BSD License
